{
  "market": "CN",
  "code": "000902",
  "company_id": "CN:000902",
  "name": "新洋丰",
  "name_en": null,
  "industry": null,
  "currency": "CNY",
  "financials": {
    "annual": [
      {
        "period": "2024",
        "revenue": 15563414716.65,
        "net_profit": 1314985692.16,
        "operating_cash_flow": 722945904.75,
        "accounts_receivable": 299514499.38,
        "inventory": 3590513869.95,
        "goodwill": null,
        "total_assets": 18230999230.04,
        "total_liabilities": 7232699630.41,
        "non_recurring_items": null,
        "related_party_revenue": null,
        "rd_capitalization_rate": null,
        "audit_opinion": null,
        "source": "akshare_sina",
        "unit": "base_currency",
        "as_of": "2024-12-31"
      },
      {
        "period": "2023",
        "revenue": 15099868971.01,
        "net_profit": 1206563575.61,
        "operating_cash_flow": 2131423510.27,
        "accounts_receivable": 206087811.7,
        "inventory": 2700506775.06,
        "goodwill": null,
        "total_assets": 16884693648.26,
        "total_liabilities": 6871810101.61,
        "non_recurring_items": null,
        "related_party_revenue": null,
        "rd_capitalization_rate": null,
        "audit_opinion": null,
        "source": "akshare_sina",
        "unit": "base_currency",
        "as_of": "2023-12-31"
      },
      {
        "period": "2022",
        "revenue": 15957732912.29,
        "net_profit": 1309353270.48,
        "operating_cash_flow": 2102482968.92,
        "accounts_receivable": 306260318.31,
        "inventory": 3216625088.78,
        "goodwill": null,
        "total_assets": 16839198700.77,
        "total_liabilities": 7824544409.88,
        "non_recurring_items": null,
        "related_party_revenue": null,
        "rd_capitalization_rate": null,
        "audit_opinion": null,
        "source": "akshare_sina",
        "unit": "base_currency",
        "as_of": "2022-12-31"
      },
      {
        "period": "2021",
        "revenue": 11801526609.22,
        "net_profit": 1208353528.62,
        "operating_cash_flow": 331611792.55,
        "accounts_receivable": 278409229.16,
        "inventory": 2643803439.9,
        "goodwill": null,
        "total_assets": 13219206077.25,
        "total_liabilities": 4921978971.01,
        "non_recurring_items": null,
        "related_party_revenue": null,
        "rd_capitalization_rate": null,
        "audit_opinion": null,
        "source": "akshare_sina",
        "unit": "base_currency",
        "as_of": "2021-12-31"
      },
      {
        "period": "2020",
        "revenue": 10068533177.44,
        "net_profit": 943458935.89,
        "operating_cash_flow": 2571177399.04,
        "accounts_receivable": 188454378.11,
        "inventory": 2095332874.43,
        "goodwill": null,
        "total_assets": 11665896200.78,
        "total_liabilities": 4487707305.24,
        "non_recurring_items": null,
        "related_party_revenue": null,
        "rd_capitalization_rate": null,
        "audit_opinion": null,
        "source": "akshare_sina",
        "unit": "base_currency",
        "as_of": "2020-12-31"
      },
      {
        "period": "2019",
        "revenue": 9327498430.06,
        "net_profit": 651053895.47,
        "operating_cash_flow": 1505624086.66,
        "accounts_receivable": 207783600.09,
        "inventory": 2438212733.11,
        "goodwill": null,
        "total_assets": 9718081275.16,
        "total_liabilities": 3022950847.68,
        "non_recurring_items": null,
        "related_party_revenue": null,
        "rd_capitalization_rate": null,
        "audit_opinion": null,
        "source": "akshare_sina",
        "unit": "base_currency",
        "as_of": "2019-12-31"
      },
      {
        "period": "2018",
        "revenue": 10030621687.25,
        "net_profit": 818841831.98,
        "operating_cash_flow": 185400811.03,
        "accounts_receivable": 194174012.33,
        "inventory": 2716347851.5,
        "goodwill": null,
        "total_assets": 8998849250.28,
        "total_liabilities": 2623137404.99,
        "non_recurring_items": null,
        "related_party_revenue": null,
        "rd_capitalization_rate": null,
        "audit_opinion": null,
        "source": "akshare_sina",
        "unit": "base_currency",
        "as_of": "2018-12-31"
      },
      {
        "period": "2017",
        "revenue": 9032401934.34,
        "net_profit": 680150701.31,
        "operating_cash_flow": 915195555.83,
        "accounts_receivable": 95469215.5,
        "inventory": 2060999984.9,
        "goodwill": null,
        "total_assets": 8745224645.22,
        "total_liabilities": 2908723508.53,
        "non_recurring_items": null,
        "related_party_revenue": null,
        "rd_capitalization_rate": null,
        "audit_opinion": null,
        "source": "akshare_sina",
        "unit": "base_currency",
        "as_of": "2017-12-31"
      },
      {
        "period": "2016",
        "revenue": 8276339924.48,
        "net_profit": 563086671.37,
        "operating_cash_flow": 750425853.27,
        "accounts_receivable": 56338131.19,
        "inventory": 1779052648.74,
        "goodwill": null,
        "total_assets": 7889011060.64,
        "total_liabilities": 2549704885.55,
        "non_recurring_items": null,
        "related_party_revenue": null,
        "rd_capitalization_rate": null,
        "audit_opinion": null,
        "source": "akshare_sina",
        "unit": "base_currency",
        "as_of": "2016-12-31"
      },
      {
        "period": "2015",
        "revenue": 9619084397.04,
        "net_profit": 747628736.0,
        "operating_cash_flow": 644058089.68,
        "accounts_receivable": 49321418.56,
        "inventory": 1551002200.41,
        "goodwill": null,
        "total_assets": 6970489620.15,
        "total_liabilities": 1968929213.52,
        "non_recurring_items": null,
        "related_party_revenue": null,
        "rd_capitalization_rate": null,
        "audit_opinion": null,
        "source": "akshare_sina",
        "unit": "base_currency",
        "as_of": "2015-12-31"
      },
      {
        "period": "2014",
        "revenue": 8352225056.56,
        "net_profit": 571091075.66,
        "operating_cash_flow": 651535153.92,
        "accounts_receivable": 20479770.0,
        "inventory": 1401027991.33,
        "goodwill": null,
        "total_assets": 5186120081.2,
        "total_liabilities": 2266956789.64,
        "non_recurring_items": null,
        "related_party_revenue": null,
        "rd_capitalization_rate": null,
        "audit_opinion": null,
        "source": "akshare_sina",
        "unit": "base_currency",
        "as_of": "2014-12-31"
      },
      {
        "period": "2013",
        "revenue": 6889143022.34,
        "net_profit": 429739809.21,
        "operating_cash_flow": 887135782.53,
        "accounts_receivable": 3642324.49,
        "inventory": 1041419700.41,
        "goodwill": null,
        "total_assets": 4681059917.14,
        "total_liabilities": 2378758113.14,
        "non_recurring_items": null,
        "related_party_revenue": null,
        "rd_capitalization_rate": null,
        "audit_opinion": null,
        "source": "akshare_sina",
        "unit": "base_currency",
        "as_of": "2013-12-31"
      },
      {
        "period": "2012",
        "revenue": 1565283952.47,
        "net_profit": -44174764.29,
        "operating_cash_flow": -49579705.87,
        "accounts_receivable": 137600667.86,
        "inventory": 245369002.88,
        "goodwill": null,
        "total_assets": 1147768726.84,
        "total_liabilities": 785455810.88,
        "non_recurring_items": null,
        "related_party_revenue": null,
        "rd_capitalization_rate": null,
        "audit_opinion": null,
        "source": "akshare_sina",
        "unit": "base_currency",
        "as_of": "2012-12-31"
      },
      {
        "period": "2011",
        "revenue": 1775150962.43,
        "net_profit": 2928739.31,
        "operating_cash_flow": 20281281.48,
        "accounts_receivable": 204570070.65,
        "inventory": 136574338.64,
        "goodwill": null,
        "total_assets": 1214455653.04,
        "total_liabilities": 805156845.83,
        "non_recurring_items": null,
        "related_party_revenue": null,
        "rd_capitalization_rate": null,
        "audit_opinion": null,
        "source": "akshare_sina",
        "unit": "base_currency",
        "as_of": "2011-12-31"
      },
      {
        "period": "2010",
        "revenue": 2039220760.25,
        "net_profit": 16057463.73,
        "operating_cash_flow": 107692820.46,
        "accounts_receivable": 157574668.43,
        "inventory": 180774151.97,
        "goodwill": null,
        "total_assets": 1297336328.13,
        "total_liabilities": 881709603.12,
        "non_recurring_items": null,
        "related_party_revenue": null,
        "rd_capitalization_rate": null,
        "audit_opinion": null,
        "source": "akshare_sina",
        "unit": "base_currency",
        "as_of": "2010-12-31"
      },
      {
        "period": "2009",
        "revenue": 1621664573.07,
        "net_profit": -48610616.66,
        "operating_cash_flow": 45562392.73,
        "accounts_receivable": 152940151.68,
        "inventory": 207881074.94,
        "goodwill": null,
        "total_assets": 1278523108.4,
        "total_liabilities": 876050890.73,
        "non_recurring_items": null,
        "related_party_revenue": null,
        "rd_capitalization_rate": null,
        "audit_opinion": null,
        "source": "akshare_sina",
        "unit": "base_currency",
        "as_of": "2009-12-31"
      },
      {
        "period": "2008",
        "revenue": 2021159311.49,
        "net_profit": -47775684.92,
        "operating_cash_flow": 30248496.44,
        "accounts_receivable": 119902064.76,
        "inventory": 182709256.94,
        "goodwill": null,
        "total_assets": 1206343336.4,
        "total_liabilities": 754332144.87,
        "non_recurring_items": null,
        "related_party_revenue": null,
        "rd_capitalization_rate": null,
        "audit_opinion": null,
        "source": "akshare_sina",
        "unit": "base_currency",
        "as_of": "2008-12-31"
      },
      {
        "period": "2007",
        "revenue": 2214688784.73,
        "net_profit": 6021707.73,
        "operating_cash_flow": 12174594.86,
        "accounts_receivable": 152509266.67,
        "inventory": 170267303.48,
        "goodwill": null,
        "total_assets": 1191899053.43,
        "total_liabilities": 680906258.24,
        "non_recurring_items": null,
        "related_party_revenue": null,
        "rd_capitalization_rate": null,
        "audit_opinion": null,
        "source": "akshare_sina",
        "unit": "base_currency",
        "as_of": "2007-12-31"
      },
      {
        "period": "2006",
        "revenue": 1910795017.82,
        "net_profit": 12953526.03,
        "operating_cash_flow": 97322930.38,
        "accounts_receivable": 138798884.66,
        "inventory": 135496686.67,
        "goodwill": null,
        "total_assets": 1195068385.79,
        "total_liabilities": 695977081.4,
        "non_recurring_items": null,
        "related_party_revenue": null,
        "rd_capitalization_rate": null,
        "audit_opinion": null,
        "source": "akshare_sina",
        "unit": "base_currency",
        "as_of": "2006-12-31"
      },
      {
        "period": "2005",
        "revenue": 1660294849.5,
        "net_profit": 4032006.11,
        "operating_cash_flow": -26953674.76,
        "accounts_receivable": 124112852.93,
        "inventory": 201166149.61,
        "goodwill": null,
        "total_assets": 1140691096.19,
        "total_liabilities": 687264156.01,
        "non_recurring_items": null,
        "related_party_revenue": null,
        "rd_capitalization_rate": null,
        "audit_opinion": null,
        "source": "akshare_sina",
        "unit": "base_currency",
        "as_of": "2005-12-31"
      },
      {
        "period": "2004",
        "revenue": 1417145069.47,
        "net_profit": 3191835.81,
        "operating_cash_flow": 258552748.92,
        "accounts_receivable": 142170092.16,
        "inventory": 101745550.78,
        "goodwill": null,
        "total_assets": 945835069.27,
        "total_liabilities": 527970656.62,
        "non_recurring_items": null,
        "related_party_revenue": null,
        "rd_capitalization_rate": null,
        "audit_opinion": null,
        "source": "akshare_sina",
        "unit": "base_currency",
        "as_of": "2004-12-31"
      },
      {
        "period": "2003",
        "revenue": 494455468.1,
        "net_profit": -135516468.77,
        "operating_cash_flow": 34204754.31,
        "accounts_receivable": 197948564.83,
        "inventory": 103126324.01,
        "goodwill": null,
        "total_assets": 964412411.2,
        "total_liabilities": 598900376.86,
        "non_recurring_items": null,
        "related_party_revenue": null,
        "rd_capitalization_rate": null,
        "audit_opinion": null,
        "source": "akshare_sina",
        "unit": "base_currency",
        "as_of": "2003-12-31"
      },
      {
        "period": "2002",
        "revenue": 515663878.86,
        "net_profit": 2164872.88,
        "operating_cash_flow": 13479924.44,
        "accounts_receivable": 224192833.61,
        "inventory": 174003328.49,
        "goodwill": null,
        "total_assets": 984294212.13,
        "total_liabilities": 478624251.84,
        "non_recurring_items": null,
        "related_party_revenue": null,
        "rd_capitalization_rate": null,
        "audit_opinion": null,
        "source": "akshare_sina",
        "unit": "base_currency",
        "as_of": "2002-12-31"
      },
      {
        "period": "2001",
        "revenue": 453935270.78,
        "net_profit": -20596031.05,
        "operating_cash_flow": -63746356.64,
        "accounts_receivable": 141129139.64,
        "inventory": 229569254.23,
        "goodwill": null,
        "total_assets": 1094546814.72,
        "total_liabilities": 574302327.93,
        "non_recurring_items": null,
        "related_party_revenue": null,
        "rd_capitalization_rate": null,
        "audit_opinion": null,
        "source": "akshare_sina",
        "unit": "base_currency",
        "as_of": "2001-12-31"
      },
      {
        "period": "2000",
        "revenue": 524337259.22,
        "net_profit": 33838453.8,
        "operating_cash_flow": 36867701.59,
        "accounts_receivable": 135872328.99,
        "inventory": 158460475.92,
        "goodwill": null,
        "total_assets": 1056609196.37,
        "total_liabilities": 460099652.23,
        "non_recurring_items": null,
        "related_party_revenue": null,
        "rd_capitalization_rate": null,
        "audit_opinion": null,
        "source": "akshare_sina",
        "unit": "base_currency",
        "as_of": "2000-12-31"
      },
      {
        "period": "1999",
        "revenue": 295648459.96,
        "net_profit": 32101256.95,
        "operating_cash_flow": -34789802.07,
        "accounts_receivable": 86196652.16,
        "inventory": 49392563.11,
        "goodwill": null,
        "total_assets": 945815580.74,
        "total_liabilities": 352424656.62,
        "non_recurring_items": null,
        "related_party_revenue": null,
        "rd_capitalization_rate": null,
        "audit_opinion": null,
        "source": "akshare_sina",
        "unit": "base_currency",
        "as_of": "1999-12-31"
      },
      {
        "period": "1998",
        "revenue": 259210944.0,
        "net_profit": 51410650.0,
        "operating_cash_flow": null,
        "accounts_receivable": 81329337.0,
        "inventory": 47934931.0,
        "goodwill": null,
        "total_assets": 455304840.0,
        "total_liabilities": 177608294.0,
        "non_recurring_items": null,
        "related_party_revenue": null,
        "rd_capitalization_rate": null,
        "audit_opinion": null,
        "source": "akshare_sina",
        "unit": "base_currency",
        "as_of": "1998-12-31"
      },
      {
        "period": "1997",
        "revenue": 237192557.0,
        "net_profit": 47748888.0,
        "operating_cash_flow": null,
        "accounts_receivable": 61605676.0,
        "inventory": 33571207.0,
        "goodwill": null,
        "total_assets": 397778874.0,
        "total_liabilities": 178981960.0,
        "non_recurring_items": null,
        "related_party_revenue": null,
        "rd_capitalization_rate": null,
        "audit_opinion": null,
        "source": "akshare_sina",
        "unit": "base_currency",
        "as_of": "1997-12-31"
      },
      {
        "period": "1996",
        "revenue": 218870132.0,
        "net_profit": 46970398.0,
        "operating_cash_flow": null,
        "accounts_receivable": 2812647.0,
        "inventory": 38655207.0,
        "goodwill": null,
        "total_assets": 263526350.0,
        "total_liabilities": 108821072.0,
        "non_recurring_items": null,
        "related_party_revenue": null,
        "rd_capitalization_rate": null,
        "audit_opinion": null,
        "source": "akshare_sina",
        "unit": "base_currency",
        "as_of": "1996-12-31"
      }
    ]
  },
  "governance": {},
  "equity_structure": [],
  "coverage": {
    "available_rules": [
      "F1",
      "F2",
      "F3"
    ],
    "missing_fields": [
      "governance"
    ]
  }
}