{
  "market": "CN",
  "code": "001872",
  "company_id": "CN:001872",
  "name": "招商港口",
  "name_en": null,
  "industry": null,
  "currency": "CNY",
  "financials": {
    "annual": [
      {
        "period": "2025",
        "revenue": 17246382527.85,
        "net_profit": 4611352247.98,
        "operating_cash_flow": 8174432389.05,
        "accounts_receivable": 1297166857.7,
        "inventory": 307216425.15,
        "goodwill": 6176416050.77,
        "total_assets": 205014697494.68,
        "total_liabilities": 73713649295.83,
        "non_recurring_items": null,
        "related_party_revenue": null,
        "rd_capitalization_rate": null,
        "audit_opinion": null,
        "source": "akshare_sina",
        "unit": "base_currency",
        "as_of": "2025-12-31"
      },
      {
        "period": "2024",
        "revenue": 16130778028.24,
        "net_profit": 4516301317.16,
        "operating_cash_flow": 8013212824.4,
        "accounts_receivable": 1193408383.78,
        "inventory": 269958020.34,
        "goodwill": 5933310929.34,
        "total_assets": 201517851881.45,
        "total_liabilities": 73359413107.2,
        "non_recurring_items": null,
        "related_party_revenue": null,
        "rd_capitalization_rate": null,
        "audit_opinion": null,
        "source": "akshare_sina",
        "unit": "base_currency",
        "as_of": "2024-12-31"
      },
      {
        "period": "2023",
        "revenue": 15750475780.22,
        "net_profit": 3571800762.16,
        "operating_cash_flow": 6579606635.17,
        "accounts_receivable": 1103901466.25,
        "inventory": 218898192.87,
        "goodwill": 6493002246.44,
        "total_assets": 198557296667.26,
        "total_liabilities": 72987362238.45,
        "non_recurring_items": null,
        "related_party_revenue": null,
        "rd_capitalization_rate": null,
        "audit_opinion": null,
        "source": "akshare_sina",
        "unit": "base_currency",
        "as_of": "2023-12-31"
      },
      {
        "period": "2022",
        "revenue": 16230489127.55,
        "net_profit": 3338693816.7,
        "operating_cash_flow": 6920377390.35,
        "accounts_receivable": 1276149689.44,
        "inventory": 225122821.48,
        "goodwill": 6411426891.09,
        "total_assets": 197587102447.31003,
        "total_liabilities": 69265494218.0,
        "non_recurring_items": null,
        "related_party_revenue": null,
        "rd_capitalization_rate": null,
        "audit_opinion": null,
        "source": "akshare_sina",
        "unit": "base_currency",
        "as_of": "2022-12-31"
      },
      {
        "period": "2021",
        "revenue": 15283808174.6,
        "net_profit": 2685829204.07,
        "operating_cash_flow": 6510326570.48,
        "accounts_receivable": 1320577577.81,
        "inventory": 194920136.12,
        "goodwill": 6024160942.07,
        "total_assets": 175984101168.66,
        "total_liabilities": 64948674277.18,
        "non_recurring_items": null,
        "related_party_revenue": null,
        "rd_capitalization_rate": null,
        "audit_opinion": null,
        "source": "akshare_sina",
        "unit": "base_currency",
        "as_of": "2021-12-31"
      },
      {
        "period": "2020",
        "revenue": 12756744317.91,
        "net_profit": 2073844409.04,
        "operating_cash_flow": 5551289013.01,
        "accounts_receivable": 1393349417.02,
        "inventory": 214823976.3,
        "goodwill": 6675939930.13,
        "total_assets": 168728326345.77,
        "total_liabilities": 62926669732.24,
        "non_recurring_items": null,
        "related_party_revenue": null,
        "rd_capitalization_rate": null,
        "audit_opinion": null,
        "source": "akshare_sina",
        "unit": "base_currency",
        "as_of": "2020-12-31"
      },
      {
        "period": "2019",
        "revenue": 12123829423.74,
        "net_profit": 2898192168.84,
        "operating_cash_flow": 5501873415.94,
        "accounts_receivable": 1356460129.9,
        "inventory": 163980192.08,
        "goodwill": 8023659694.81,
        "total_assets": 156696917845.87003,
        "total_liabilities": 61706710233.63,
        "non_recurring_items": null,
        "related_party_revenue": null,
        "rd_capitalization_rate": null,
        "audit_opinion": null,
        "source": "akshare_sina",
        "unit": "base_currency",
        "as_of": "2019-12-31"
      },
      {
        "period": "2018",
        "revenue": 9703394622.58,
        "net_profit": 1090418910.77,
        "operating_cash_flow": 4288575424.84,
        "accounts_receivable": 1109230503.08,
        "inventory": 108567270.02,
        "goodwill": 8335895842.35,
        "total_assets": 128018084415.68,
        "total_liabilities": 47601158542.87,
        "non_recurring_items": null,
        "related_party_revenue": null,
        "rd_capitalization_rate": null,
        "audit_opinion": null,
        "source": "akshare_sina",
        "unit": "base_currency",
        "as_of": "2018-12-31"
      },
      {
        "period": "2017",
        "revenue": 7544635284.96,
        "net_profit": 2365214907.45,
        "operating_cash_flow": 3475037036.28,
        "accounts_receivable": 257081961.83,
        "inventory": 82789282.22,
        "goodwill": 4051665903.24,
        "total_assets": 109304242691.71,
        "total_liabilities": 35214687303.89,
        "non_recurring_items": null,
        "related_party_revenue": null,
        "rd_capitalization_rate": null,
        "audit_opinion": null,
        "source": "akshare_sina",
        "unit": "base_currency",
        "as_of": "2017-12-31"
      },
      {
        "period": "2016",
        "revenue": 2381483399.94,
        "net_profit": 532376492.97,
        "operating_cash_flow": 1121032625.07,
        "accounts_receivable": 214806648.35,
        "inventory": 22011047.53,
        "goodwill": 10858898.17,
        "total_assets": 7792570272.01,
        "total_liabilities": 1308824703.15,
        "non_recurring_items": null,
        "related_party_revenue": null,
        "rd_capitalization_rate": null,
        "audit_opinion": null,
        "source": "akshare_sina",
        "unit": "base_currency",
        "as_of": "2016-12-31"
      },
      {
        "period": "2015",
        "revenue": 1872608596.16,
        "net_profit": 527751492.42,
        "operating_cash_flow": 977850737.45,
        "accounts_receivable": 189016564.86,
        "inventory": 17300307.66,
        "goodwill": 10858898.17,
        "total_assets": 6913772876.99,
        "total_liabilities": 1684462446.87,
        "non_recurring_items": null,
        "related_party_revenue": null,
        "rd_capitalization_rate": null,
        "audit_opinion": null,
        "source": "akshare_sina",
        "unit": "base_currency",
        "as_of": "2015-12-31"
      },
      {
        "period": "2014",
        "revenue": 1804766176.31,
        "net_profit": 417594271.33,
        "operating_cash_flow": 818315147.74,
        "accounts_receivable": 203641944.62,
        "inventory": 19090168.61,
        "goodwill": 10858898.17,
        "total_assets": 6935824199.68,
        "total_liabilities": 2060224599.25,
        "non_recurring_items": null,
        "related_party_revenue": null,
        "rd_capitalization_rate": null,
        "audit_opinion": null,
        "source": "akshare_sina",
        "unit": "base_currency",
        "as_of": "2014-12-31"
      },
      {
        "period": "2013",
        "revenue": 1780774836.3,
        "net_profit": 502894547.79,
        "operating_cash_flow": 897178297.23,
        "accounts_receivable": 223441476.99,
        "inventory": 21253356.18,
        "goodwill": 10858898.17,
        "total_assets": 7346529214.7,
        "total_liabilities": 2618453032.83,
        "non_recurring_items": null,
        "related_party_revenue": null,
        "rd_capitalization_rate": null,
        "audit_opinion": null,
        "source": "akshare_sina",
        "unit": "base_currency",
        "as_of": "2013-12-31"
      },
      {
        "period": "2012",
        "revenue": 1783846134.76,
        "net_profit": 467103270.43,
        "operating_cash_flow": 698472452.71,
        "accounts_receivable": 251420961.37,
        "inventory": 21325571.29,
        "goodwill": 10858898.17,
        "total_assets": 6781130451.1,
        "total_liabilities": 2316120545.66,
        "non_recurring_items": null,
        "related_party_revenue": null,
        "rd_capitalization_rate": null,
        "audit_opinion": null,
        "source": "akshare_sina",
        "unit": "base_currency",
        "as_of": "2012-12-31"
      },
      {
        "period": "2011",
        "revenue": 1708136899.0,
        "net_profit": 505645137.0,
        "operating_cash_flow": 746190596.0,
        "accounts_receivable": 230797003.0,
        "inventory": 23500358.0,
        "goodwill": 10858898.0,
        "total_assets": 6540228435.0,
        "total_liabilities": 2434164364.0,
        "non_recurring_items": null,
        "related_party_revenue": null,
        "rd_capitalization_rate": null,
        "audit_opinion": null,
        "source": "akshare_sina",
        "unit": "base_currency",
        "as_of": "2011-12-31"
      },
      {
        "period": "2010",
        "revenue": 1740417668.0,
        "net_profit": 596680156.0,
        "operating_cash_flow": 926845569.0,
        "accounts_receivable": 179772755.0,
        "inventory": 23888526.0,
        "goodwill": 10858898.0,
        "total_assets": 6202184742.0,
        "total_liabilities": 2395026910.0,
        "non_recurring_items": null,
        "related_party_revenue": null,
        "rd_capitalization_rate": null,
        "audit_opinion": null,
        "source": "akshare_sina",
        "unit": "base_currency",
        "as_of": "2010-12-31"
      },
      {
        "period": "2009",
        "revenue": 1465434512.0,
        "net_profit": 418864844.0,
        "operating_cash_flow": 726501993.0,
        "accounts_receivable": 209177364.0,
        "inventory": 25616306.0,
        "goodwill": 10858898.0,
        "total_assets": 5527873569.0,
        "total_liabilities": 2107282039.0,
        "non_recurring_items": null,
        "related_party_revenue": null,
        "rd_capitalization_rate": null,
        "audit_opinion": null,
        "source": "akshare_sina",
        "unit": "base_currency",
        "as_of": "2009-12-31"
      },
      {
        "period": "2008",
        "revenue": 1914007717.0,
        "net_profit": 642891604.0,
        "operating_cash_flow": 1090354989.0,
        "accounts_receivable": 145675880.0,
        "inventory": 27808298.0,
        "goodwill": 10858898.0,
        "total_assets": 5153728048.0,
        "total_liabilities": 1826070671.0,
        "non_recurring_items": null,
        "related_party_revenue": null,
        "rd_capitalization_rate": null,
        "audit_opinion": null,
        "source": "akshare_sina",
        "unit": "base_currency",
        "as_of": "2008-12-31"
      },
      {
        "period": "2007",
        "revenue": 2003562530.0,
        "net_profit": 663872167.0,
        "operating_cash_flow": 1197492986.0,
        "accounts_receivable": 217005190.0,
        "inventory": 24629401.0,
        "goodwill": 10858898.0,
        "total_assets": 5457335718.0,
        "total_liabilities": 2312713967.0,
        "non_recurring_items": null,
        "related_party_revenue": null,
        "rd_capitalization_rate": null,
        "audit_opinion": null,
        "source": "akshare_sina",
        "unit": "base_currency",
        "as_of": "2007-12-31"
      },
      {
        "period": "2006",
        "revenue": 1948638423.0,
        "net_profit": 626836148.0,
        "operating_cash_flow": 1146012470.0,
        "accounts_receivable": 240323715.0,
        "inventory": 23603514.0,
        "goodwill": 10858898.0,
        "total_assets": 4605598614.0,
        "total_liabilities": 1534168823.0,
        "non_recurring_items": null,
        "related_party_revenue": null,
        "rd_capitalization_rate": null,
        "audit_opinion": null,
        "source": "akshare_sina",
        "unit": "base_currency",
        "as_of": "2006-12-31"
      },
      {
        "period": "2005",
        "revenue": 1796025268.0,
        "net_profit": 583452604.0,
        "operating_cash_flow": 1216120674.0,
        "accounts_receivable": 235594322.0,
        "inventory": 21883638.0,
        "goodwill": null,
        "total_assets": 4573762884.0,
        "total_liabilities": 1538266411.0,
        "non_recurring_items": null,
        "related_party_revenue": null,
        "rd_capitalization_rate": null,
        "audit_opinion": null,
        "source": "akshare_sina",
        "unit": "base_currency",
        "as_of": "2005-12-31"
      },
      {
        "period": "2004",
        "revenue": 1568099966.0,
        "net_profit": 535628927.0,
        "operating_cash_flow": 1037507002.0,
        "accounts_receivable": 224481675.0,
        "inventory": 22792039.0,
        "goodwill": null,
        "total_assets": 4257118245.0,
        "total_liabilities": 1704389817.0,
        "non_recurring_items": null,
        "related_party_revenue": null,
        "rd_capitalization_rate": null,
        "audit_opinion": null,
        "source": "akshare_sina",
        "unit": "base_currency",
        "as_of": "2004-12-31"
      },
      {
        "period": "2003",
        "revenue": 1056619065.0,
        "net_profit": 313987876.0,
        "operating_cash_flow": 602643122.0,
        "accounts_receivable": 178197639.0,
        "inventory": 19954765.0,
        "goodwill": null,
        "total_assets": 3214220100.0,
        "total_liabilities": 1219427171.0,
        "non_recurring_items": null,
        "related_party_revenue": null,
        "rd_capitalization_rate": null,
        "audit_opinion": null,
        "source": "akshare_sina",
        "unit": "base_currency",
        "as_of": "2003-12-31"
      },
      {
        "period": "2002",
        "revenue": 745564278.0,
        "net_profit": 183599988.0,
        "operating_cash_flow": 417866767.0,
        "accounts_receivable": 125981417.0,
        "inventory": 19720491.0,
        "goodwill": null,
        "total_assets": 2331627234.0,
        "total_liabilities": 657477429.0,
        "non_recurring_items": null,
        "related_party_revenue": null,
        "rd_capitalization_rate": null,
        "audit_opinion": null,
        "source": "akshare_sina",
        "unit": "base_currency",
        "as_of": "2002-12-31"
      },
      {
        "period": "2001",
        "revenue": 487387983.0,
        "net_profit": 90276435.0,
        "operating_cash_flow": 226743727.0,
        "accounts_receivable": 108275889.0,
        "inventory": 18531049.0,
        "goodwill": null,
        "total_assets": 2223564238.0,
        "total_liabilities": 847838633.0,
        "non_recurring_items": null,
        "related_party_revenue": null,
        "rd_capitalization_rate": null,
        "audit_opinion": null,
        "source": "akshare_sina",
        "unit": "base_currency",
        "as_of": "2001-12-31"
      },
      {
        "period": "2000",
        "revenue": 442571303.34,
        "net_profit": 82561186.26,
        "operating_cash_flow": 214328310.33,
        "accounts_receivable": 101022659.49,
        "inventory": 17255241.3,
        "goodwill": null,
        "total_assets": 2252338533.67,
        "total_liabilities": 1002065687.45,
        "non_recurring_items": null,
        "related_party_revenue": null,
        "rd_capitalization_rate": null,
        "audit_opinion": null,
        "source": "akshare_sina",
        "unit": "base_currency",
        "as_of": "2000-12-31"
      },
      {
        "period": "1999",
        "revenue": 388236934.36,
        "net_profit": 72446699.78,
        "operating_cash_flow": 162935139.32,
        "accounts_receivable": 106528018.46,
        "inventory": 12020326.24,
        "goodwill": null,
        "total_assets": 1747586132.03,
        "total_liabilities": 547931857.23,
        "non_recurring_items": null,
        "related_party_revenue": null,
        "rd_capitalization_rate": null,
        "audit_opinion": null,
        "source": "akshare_sina",
        "unit": "base_currency",
        "as_of": "1999-12-31"
      },
      {
        "period": "1998",
        "revenue": 330127676.35,
        "net_profit": 55411194.93,
        "operating_cash_flow": 122963430.56,
        "accounts_receivable": 75357103.34,
        "inventory": 14640860.52,
        "goodwill": null,
        "total_assets": 1683972239.31,
        "total_liabilities": 533407496.87,
        "non_recurring_items": null,
        "related_party_revenue": null,
        "rd_capitalization_rate": null,
        "audit_opinion": null,
        "source": "akshare_sina",
        "unit": "base_currency",
        "as_of": "1998-12-31"
      },
      {
        "period": "1997",
        "revenue": 398470231.97,
        "net_profit": 93340126.21,
        "operating_cash_flow": null,
        "accounts_receivable": 81701413.56,
        "inventory": 19871244.05,
        "goodwill": null,
        "total_assets": 1560673252.54,
        "total_liabilities": 351666720.23,
        "non_recurring_items": null,
        "related_party_revenue": null,
        "rd_capitalization_rate": null,
        "audit_opinion": null,
        "source": "akshare_sina",
        "unit": "base_currency",
        "as_of": "1997-12-31"
      },
      {
        "period": "1996",
        "revenue": 409863891.7,
        "net_profit": 107302420.79,
        "operating_cash_flow": null,
        "accounts_receivable": 72498858.51,
        "inventory": 22291447.66,
        "goodwill": null,
        "total_assets": 1468098565.74,
        "total_liabilities": 402683757.44,
        "non_recurring_items": null,
        "related_party_revenue": null,
        "rd_capitalization_rate": null,
        "audit_opinion": null,
        "source": "akshare_sina",
        "unit": "base_currency",
        "as_of": "1996-12-31"
      },
      {
        "period": "1995",
        "revenue": 435362169.48,
        "net_profit": 124362363.25,
        "operating_cash_flow": null,
        "accounts_receivable": 39984165.17,
        "inventory": 18067771.79,
        "goodwill": null,
        "total_assets": 1214102128.51,
        "total_liabilities": 294050686.7,
        "non_recurring_items": null,
        "related_party_revenue": null,
        "rd_capitalization_rate": null,
        "audit_opinion": null,
        "source": "akshare_sina",
        "unit": "base_currency",
        "as_of": "1995-12-31"
      },
      {
        "period": "1994",
        "revenue": 350320005.79,
        "net_profit": 112479608.37,
        "operating_cash_flow": null,
        "accounts_receivable": 29042254.66,
        "inventory": 18827860.16,
        "goodwill": null,
        "total_assets": 1010181201.26,
        "total_liabilities": 260244229.77,
        "non_recurring_items": null,
        "related_party_revenue": null,
        "rd_capitalization_rate": null,
        "audit_opinion": null,
        "source": "akshare_sina",
        "unit": "base_currency",
        "as_of": "1994-12-31"
      },
      {
        "period": "1993",
        "revenue": 251825311.48,
        "net_profit": 90676446.26,
        "operating_cash_flow": null,
        "accounts_receivable": 84915621.45,
        "inventory": 11330306.42,
        "goodwill": null,
        "total_assets": 889414935.53,
        "total_liabilities": 215725723.41,
        "non_recurring_items": null,
        "related_party_revenue": null,
        "rd_capitalization_rate": null,
        "audit_opinion": null,
        "source": "akshare_sina",
        "unit": "base_currency",
        "as_of": "1993-12-31"
      }
    ]
  },
  "governance": {},
  "equity_structure": [],
  "coverage": {
    "available_rules": [
      "F1",
      "F2",
      "F3"
    ],
    "missing_fields": [
      "governance"
    ]
  }
}